LICENSE
README.md
setup.py
src/app.py
src/config.py
src/AudioDetection/Audio.py
src/AudioDetection/AudioDetector.py
src/AudioDetection/ShortTermFeatures.py
src/AudioDetection/WavAudio.py
src/AudioDetection/__init__.py
src/AudioDetection/audioBasicIO.py
src/AudioDetection/audioSegmentation.py
src/AudioDetection/audioTrainTest.py
src/AudioExtraction/AudioExtractor.py
src/AudioExtraction/Mp4Video.py
src/AudioExtraction/Video.py
src/AudioExtraction/__init__.py
src/AudioPlayer/__init__.py
src/AudioSeparation/AudioSeparator.py
src/AudioSeparation/__init__.py
src/AudioVideoMerge/AudioVideoMerger.py
src/AudioVideoMerge/__init__.py
src/Compression/Compressor.py
src/Compression/__init__.py
src/FaceDetection/FaceDetector.py
src/FaceDetection/__init__.py
src/Preprocessing/__init__.py
src/Utilities/Utilities.py
src/Utilities/__init__.py
src/VideoPlayer/VideoPlayer.py
src/VideoPlayer/__init__.py
src/VideoSeparation/VideoSeparator.py
src/VideoSeparation/__init__.py
src/bhuiyans_dataset_builder.egg-info/PKG-INFO
src/bhuiyans_dataset_builder.egg-info/SOURCES.txt
src/bhuiyans_dataset_builder.egg-info/dependency_links.txt
src/bhuiyans_dataset_builder.egg-info/requires.txt
src/bhuiyans_dataset_builder.egg-info/top_level.txt