Metadata-Version: 2.1
Name: bhuiyans-dataset-builder
Version: 0.0.2
Summary: A video processing tool for visual data collection, end-to-end preprocessing, ready-to-go for model training.
Home-page: https://github.com/MasumBhuiyan/dataset-builder
Author: Masum Bhuiyan
Author-email: masumbhuiyan577@gmail.com
License: Apache License
Keywords: video preprocessing split merge video player
Platform: UNKNOWN
Classifier: Development Status :: 4 - Beta
Classifier: Intended Audience :: Developers
Classifier: Topic :: Internet
Classifier: License :: OSI Approved :: MIT License
Classifier: Programming Language :: Python :: 3
Classifier: Programming Language :: Python :: 3.3
Classifier: Programming Language :: Python :: 3.4
Classifier: Programming Language :: Python :: 3.5
License-File: LICENSE
